AUTHORS
INSTALL
LICENSE
MANIFEST.in
README.rst
setup.py
django_rinvoices.egg-info/PKG-INFO
django_rinvoices.egg-info/SOURCES.txt
django_rinvoices.egg-info/dependency_links.txt
django_rinvoices.egg-info/not-zip-safe
django_rinvoices.egg-info/requires.txt
django_rinvoices.egg-info/top_level.txt
docs/Makefile
docs/source/conf.py
docs/source/index.rst
rinvoices/__init__.py
rinvoices/admin.py
rinvoices/forms.py
rinvoices/models.py
rinvoices/tests.py
rinvoices/urls.py
rinvoices/views.py
rinvoices/locale/en/LC_MESSAGES/django.mo
rinvoices/locale/en/LC_MESSAGES/django.po
rinvoices/locale/es/LC_MESSAGES/django.mo
rinvoices/locale/es/LC_MESSAGES/django.po
rinvoices/migrations/0001_initial.py
rinvoices/migrations/0002_auto__del_field_invoice_line__add_field_line_invoice.py
rinvoices/migrations/0003_auto__chg_field_line_invoice.py
rinvoices/migrations/0004_auto__add_currency__add_tax__add_field_invoice_registered__add_field_i.py
rinvoices/migrations/0005_auto__del_field_line_ref__add_field_line_reference.py
rinvoices/migrations/0006_auto__add_invoicereceive__del_field_invoice_image__add_field_invoice_s.py
rinvoices/migrations/0007_auto__add_field_invoicereceive_title.py
rinvoices/migrations/0008_auto__add_field_invoicereceive_registered.py
rinvoices/migrations/0009_auto__add_field_invoicereceive_paid__add_field_invoice_sent__add_field.py
rinvoices/migrations/0010_auto__add_provider__add_field_invoicereceive_provider__add_field_invoi.py
rinvoices/migrations/0011_auto__add_quantityunit__add_field_line_unit.py
rinvoices/migrations/0012_auto__add_retention__add_field_invoice_retentions.py
rinvoices/migrations/0013_auto__add_field_invoice_subtotal_retentions.py
rinvoices/migrations/0014_auto__add_budget.py
rinvoices/migrations/0015_auto__add_budgetline.py
rinvoices/migrations/0016_auto__add_field_budgetline_concept__add_field_budgetline_quantity.py
rinvoices/migrations/0017_auto__add_field_budgetline_unit.py
rinvoices/migrations/0018_auto__add_field_budgetline_unit_price.py
rinvoices/migrations/0019_auto__add_field_budgetline_amount.py
rinvoices/migrations/0020_auto__chg_field_budgetline_unit.py
rinvoices/migrations/0021_auto__add_field_budget_taxes.py
