Metadata-Version: 1.1
Name: django-rinvoices
Version: 0.0.25
Summary: Yet another Django Invoicing App
Home-page: http://bitbucket.org/r0sk/django-rinvoices
Author: Oscar M. Lage Guitian
Author-email: r0sk10@gmail.com
License: BSD licence, see LICENSE file
Keywords: django application invoices
Platform: UNKNOWN
Classifier: Development Status :: 4 - Beta
Classifier: Environment :: Web Environment
Classifier: Framework :: Django
Classifier: Intended Audience :: Developers
Classifier: License :: OSI Approved :: BSD License
Classifier: Operating System :: OS Independent
Classifier: Programming Language :: Python
Classifier: Topic :: Internet :: WWW/HTTP :: Dynamic Content
Classifier: Topic :: Software Development :: Libraries :: Python Modules
